core/__init__.py
core/apps.py
core/health/__init__.py
core/health/views.py
core/middleware/__init__.py
core/middleware/security.py
core/utils/__init__.py
core/utils/caching.py
core/utils/error_handling.py
core/utils/lazy_imports.py
stubs/__init__.py
stubs/enterprise.py
wetail_core-1.0.0.dist-info/licenses/LICENSE
wetail_core-1.0.0.dist-info/METADATA
wetail_core-1.0.0.dist-info/WHEEL
wetail_core-1.0.0.dist-info/top_level.txt
wetail_core-1.0.0.dist-info/RECORD
