Metadata-Version: 2.4
Name: wetail-core
Version: 1.0.0
Summary: Wetail Core - Open-source e-commerce platform foundation
Author-email: Alton Barnes <altonbarnes7@gmail.com>
Maintainer-email: Alton Barnes <altonbarnes7@gmail.com>
License: Apache-2.0
Project-URL: Homepage, https://wetail.co
Project-URL: Documentation, https://docs.wetail.co/core
Project-URL: Repository, https://github.com/abarnes1205/Wetail_Mona_Lisa
Project-URL: Changelog, https://github.com/abarnes1205/Wetail_Mona_Lisa/blob/main/CHANGELOG.md
Project-URL: Bug Tracker, https://github.com/abarnes1205/Wetail_Mona_Lisa/issues
Keywords: django,ecommerce,marketplace,retail,shopping
Classifier: Development Status :: 4 - Beta
Classifier: Environment :: Web Environment
Classifier: Framework :: Django
Classifier: Framework :: Django :: 4.2
Classifier: Intended Audience :: Developers
Classifier: License :: OSI Approved :: Apache Software License
Classifier: Operating System :: OS Independent
Classifier: Programming Language :: Python :: 3
Classifier: Programming Language :: Python :: 3.10
Classifier: Programming Language :: Python :: 3.11
Classifier: Programming Language :: Python :: 3.12
Classifier: Topic :: Internet :: WWW/HTTP :: Dynamic Content
Classifier: Topic :: Software Development :: Libraries :: Python Modules
Requires-Python: >=3.10
License-File: LICENSE
Requires-Dist: Django<5.0,>=4.2
Requires-Dist: djangorestframework>=3.14.0
Requires-Dist: django-cors-headers>=4.3.0
Requires-Dist: django-redis>=5.4.0
Requires-Dist: psycopg2-binary>=2.9.9
Requires-Dist: python-dotenv>=1.0.0
Requires-Dist: Pillow>=10.0.0
Provides-Extra: dev
Requires-Dist: pytest>=7.4.0; extra == "dev"
Requires-Dist: pytest-django>=4.5.0; extra == "dev"
Requires-Dist: pytest-cov>=4.1.0; extra == "dev"
Requires-Dist: factory-boy>=3.3.0; extra == "dev"
Requires-Dist: black>=23.0.0; extra == "dev"
Requires-Dist: isort>=5.12.0; extra == "dev"
Requires-Dist: flake8>=6.1.0; extra == "dev"
Requires-Dist: mypy>=1.5.0; extra == "dev"
Provides-Extra: celery
Requires-Dist: celery>=5.3.4; extra == "celery"
Requires-Dist: redis>=5.0.0; extra == "celery"
Dynamic: license-file
